README.txt
setup.py
src/helloworld/__init__.py
src/helloworld/core.py
src/helloworld_2015.egg-info/PKG-INFO
src/helloworld_2015.egg-info/SOURCES.txt
src/helloworld_2015.egg-info/dependency_links.txt
src/helloworld_2015.egg-info/top_level.txt