Metadata-Version: 1.1
Name: helloworld-2015
Version: 1.0.0
Summary: just for fun!
Home-page: https://github.com/fervid
Author: Anton Romanov
Author-email: romanov.antoha@gmail.com
License: BSD
Platform: UNKNOWN
Classifier: Development Status :: 5 - Production/Stable
Classifier: Topic :: Utilities
Classifier: License :: OSI Approved :: BSD License
